Metadata-Version: 2.1
Name: odoo13-addon-stock-quant-reservation-info-mrp
Version: 13.0.1.0.1.dev3
Summary: Allows to see the manufacturing order related to the reserved info of Products
Home-page: https://github.com/OCA/stock-logistics-warehouse
Author: ForgeFlow, Odoo Community Association (OCA)
Author-email: support@odoo-community.org
License: AGPL-3
Platform: UNKNOWN
Classifier: Programming Language :: Python
Classifier: Framework :: Odoo
Classifier: Framework :: Odoo :: 13.0
Classifier: License :: OSI Approved :: GNU Affero General Public License v3
Requires-Python: >=3.5
Requires-Dist: odoo13-addon-stock-quant-reservation-info
Requires-Dist: odoo <13.1dev,>=13.0a
